apheris_preprocessing/__init__.py
apheris_preprocessing/_internal/__init__.py
apheris_preprocessing/_internal/dataframe_accessors.py
apheris_preprocessing/_internal/dataframe_client.py
apheris_preprocessing/_internal/dataframe_types.py
apheris_preprocessing/_internal/fdf_loader.py
apheris_preprocessing/_internal/privacy.py
apheris_preprocessing/_internal/remote_functions.py
apheris_preprocessing/_internal/utils/__init__.py
apheris_preprocessing/_internal/utils/commands.py
apheris_preprocessing/_internal/utils/comparison_types.py
apheris_preprocessing/_internal/utils/digraph.py
apheris_preprocessing/_internal/utils/exceptions_handling.py
apheris_preprocessing/_internal/utils/formats.py
apheris_preprocessing/_internal/utils/lazy_loader.py
apheris_preprocessing/_internal/utils/node_uuid.py
apheris_preprocessing/_internal/utils/str_object_converter.py
apheris_preprocessing/exceptions/__init__.py
apheris_preprocessing-0.9.0.dist-info/licenses/LICENSE
apheris_preprocessing-0.9.0.dist-info/METADATA
apheris_preprocessing-0.9.0.dist-info/WHEEL
apheris_preprocessing-0.9.0.dist-info/top_level.txt
apheris_preprocessing-0.9.0.dist-info/RECORD
