Metadata-Version: 2.4
Name: apheris-preprocessing
Version: 0.9.0
License-File: LICENSE
Requires-Dist: networkx==3.5.*; python_version > "3.10"
Requires-Dist: networkx==3.4.2; python_version <= "3.10"
Requires-Dist: numpy==1.26.*
Requires-Dist: pandas==1.5.*
Requires-Dist: apheris-utils==0.25.*
Requires-Dist: pyarrow==21.0.0
Requires-Dist: fastparquet==2024.11.0
Provides-Extra: dev
Requires-Dist: build==1.3.0; extra == "dev"
Requires-Dist: commitizen==4.9.1; extra == "dev"
Requires-Dist: cz-github-jira-conventional==3.0.2; extra == "dev"
Requires-Dist: flake8==7.3.0; extra == "dev"
Requires-Dist: pytest~=8.4.0; extra == "dev"
Requires-Dist: pytest-cov~=7.0.0; extra == "dev"
Requires-Dist: coverage-threshold~=0.6.2; extra == "dev"
Requires-Dist: pre-commit~=4.3.0; extra == "dev"
Provides-Extra: dummy
Requires-Dist: apheris-utils[simulator]; extra == "dummy"
Provides-Extra: remote
Requires-Dist: apheris-utils[nvflare]; extra == "remote"
Dynamic: license-file
